nonebot_plugin_customemote/__init__.py
nonebot_plugin_customemote/config.py
nonebot_plugin_customemote/data_source.py
nonebot_plugin_customemote-0.1.0.dist-info/LICENSE
nonebot_plugin_customemote-0.1.0.dist-info/METADATA
nonebot_plugin_customemote-0.1.0.dist-info/WHEEL
nonebot_plugin_customemote-0.1.0.dist-info/top_level.txt
nonebot_plugin_customemote-0.1.0.dist-info/RECORD
