Metadata-Version: 2.1
Name: nonebot-plugin-customemote
Version: 0.1.0
Summary: A plugin based on NoneBot2, send text to call your set emotes.
Home-page: https://github.com/DMCSWCG/nonebot-plugin-customemote/
Author: DMCSWCG
License: MIT License
Project-URL: Bug Tracker, https://github.com/DMCSWCG/nonebot-plugin-customemote/issues
Platform: UNKNOWN
Classifier: Programming Language :: Python :: 3
Classifier: Operating System :: OS Independent
Requires-Python: >=3.7
Requires-Dist: nonebot2 (>=2.0.0rc1)
Requires-Dist: nonebot-adapter-onebot (>=2.0.0rc1)
Requires-Dist: aiofiles
Requires-Dist: pydantic
Requires-Dist: httpx
Requires-Dist: ujson
